llmgcalparse.py
llmgcalparse-0.1.0a6.dist-info/licenses/LICENSE
llmgcalparse-0.1.0a6.dist-info/METADATA
llmgcalparse-0.1.0a6.dist-info/WHEEL
llmgcalparse-0.1.0a6.dist-info/top_level.txt
llmgcalparse-0.1.0a6.dist-info/RECORD
