Metadata-Version: 2.4
Name: llmgcalparse
Version: 0.1.0a6
Summary: Create Google Calendar event URLs interactively from a natural language description, leveraging LLMs with an OpenAI Chat Completions-compatible API and user edits.
Author-email: Jifeng Wu <jifengwu2k@gmail.com>
License-Expression: MIT
Project-URL: Homepage, https://github.com/jifengwu2k/llmgcalparse
Project-URL: Bug Tracker, https://github.com/jifengwu2k/llmgcalparse/issues
Classifier: Programming Language :: Python :: 2
Classifier: Programming Language :: Python :: 3
Classifier: Operating System :: OS Independent
Requires-Python: >=2
License-File: LICENSE
Requires-Dist: chat-completions-conversation
Requires-Dist: get-unicode-multiline-input-with-editor
Requires-Dist: textcompat
Requires-Dist: typing; python_version < "3.5"
Dynamic: license-file
